trepanxpy/__init__.py
trepanxpy/__main__.py
trepanxpy/core.py
trepanxpy/debugger.py
trepanxpy/debugger_defaults.py
trepanxpy/events.py
trepanxpy/fmt.py
trepanxpy/version.py
trepanxpy/processor/__init__.py
trepanxpy/processor/cmd.py
trepanxpy/processor/trace.py
trepanxpy/processor/command/__init__.py
trepanxpy/processor/command/continue.py
trepanxpy/processor/command/finish.py
trepanxpy/processor/command/info.py
trepanxpy/processor/command/next.py
trepanxpy/processor/command/python.py
trepanxpy/processor/command/quit.py
trepanxpy/processor/command/return.py
trepanxpy/processor/command/set.py
trepanxpy/processor/command/show.py
trepanxpy/processor/command/step.py
trepanxpy/processor/command/stepi.py
trepanxpy/processor/command/vmstack.py
trepanxpy/processor/command/info_subcmd/__init__.py
trepanxpy/processor/command/info_subcmd/blocks.py
trepanxpy/processor/command/info_subcmd/frame.py
trepanxpy/processor/command/info_subcmd/pc.py
trepanxpy/processor/command/info_subcmd/stack.py
trepanxpy/processor/command/set_subcmd/__init__.py
trepanxpy/processor/command/set_subcmd/autostack.py
trepanxpy/processor/command/set_subcmd/loglevel.py
trepanxpy/processor/command/set_subcmd/pc.py
trepanxpy/processor/command/show_subcmd/__init__.py
trepanxpy/processor/command/show_subcmd/autostack.py
trepanxpy/processor/command/show_subcmd/loglevel.py
trepanxpy/processor/command/vmstack_subcmd/__init__.py
trepanxpy/processor/command/vmstack_subcmd/peek.py
trepanxpy/processor/command/vmstack_subcmd/pop.py
trepanxpy/processor/command/vmstack_subcmd/push.py
trepanxpy-1.1.2.dist-info/METADATA
trepanxpy-1.1.2.dist-info/WHEEL
trepanxpy-1.1.2.dist-info/entry_points.txt
trepanxpy-1.1.2.dist-info/top_level.txt
trepanxpy-1.1.2.dist-info/RECORD
